raihan_arithmatic/__init__.py
raihan_arithmatic/aritmatic.py
raihan_aritmatic-0.0.1.dist-info/licenses/LICENSE
raihan_aritmatic-0.0.1.dist-info/METADATA
raihan_aritmatic-0.0.1.dist-info/WHEEL
raihan_aritmatic-0.0.1.dist-info/top_level.txt
raihan_aritmatic-0.0.1.dist-info/RECORD
