Metadata-Version: 2.4
Name: Raihan-Aritmatic
Version: 0.0.1
Summary: This is a simple arithmetic raihan_arithmatic for ADD, SUB, MUL, DIV operations.
Author: MD. Mostafa Raihan
Author-email: m.raihan.computerscience@gmail.com
Classifier: Programming Language :: Python :: 3
Classifier: License :: OSI Approved :: MIT License
Requires-Python: >=3.6
License-File: LICENSE
Dynamic: author
Dynamic: author-email
Dynamic: classifier
Dynamic: description
Dynamic: description-content-type
Dynamic: license-file
Dynamic: requires-python
Dynamic: summary
